README.md
setup.py
drivecandy/__init__.py
drivecandy/drive.py
drivecandy/exceptions.py
gcandy.egg-info/PKG-INFO
gcandy.egg-info/SOURCES.txt
gcandy.egg-info/dependency_links.txt
gcandy.egg-info/not-zip-safe
gcandy.egg-info/requires.txt
gcandy.egg-info/top_level.txt