Metadata-Version: 2.1
Name: gcandy
Version: 1.0.1
Summary: Python wrapper for Google Drive REST API.
Home-page: https://github.com/Marco-Christiani/drive-candy
Author: Marco Christiani
Author-email: mchristiani2017@gmail.com
License: GPLv3
Platform: UNKNOWN
